{
  "paper_type": "contribution",
  "triples": [
    {
      "name": "Markov chain",
      "entity_type": "concept",
      "relation": "uses",
      "relevance": "Markov automata directly extend and compose Markov chains as a foundational modeling formalism.",
      "wikipedia_url": "https://en.wikipedia.org/wiki/Markov_chain",
      "wikidata": {
        "id": "Q176645",
        "label": "Markov chain",
        "description": "stochastic model describing a sequence of possible events in which the probability of each event depends only on the state attained in the previous event",
        "aliases": [
          "Markov process",
          "Markov chains"
        ],
        "claims": {
          "P138": "Q176659",
          "P508": "19104",
          "gnd_id": "4134948-9",
          "freebase_id": "/m/0gjhm",
          "mesh_id": "D008390",
          "subclass_of": [
            "Q486902",
            "Q2221775"
          ],
          "P3285": "60J10",
          "quora_topic_id": "Markov-Chains",
          "P3827": [
            "transition-probabilities",
            "markov-chains"
          ],
          "P2812": "MarkovChain",
          "britannica_id": "topic/Markov-chain",
          "commons_category": "Markov chains",
          "image": "Markovkate 01.svg",
          "instance_of": "Q3284399",
          "mesh_tree_code": [
            "E05.318.740.600.500",
            "E05.318.740.996.500",
            "G17.830.500",
            "N05.715.360.750.625.500",
            "N05.715.360.750.770.500",
            "N06.850.520.830.600.500",
            "N06.850.520.830.996.500"
          ],
          "P1245": "382987",
          "mag_id": "98763669",
          "P4215": "Markov chain",
          "P4613": [
            "62430",
            "63754"
          ],
          "P5106": "markovchain",
          "P2924": "2187018",
          "loc_id": "sh85081369",
          "P2347": "13075",
          "P8189": "987007553386405171",
          "openalex_id": [
            "C159886148",
            "C98763669"
          ],
          "openalex_topic_id": [
            "235388",
            "296332",
            "500029"
          ],
          "P5008": {
            "id": "Q6173448",
            "label": "Wikipedia:Vital articles/Level/4"
          },
          "P2163": "1010347",
          "P268": "11932425d",
          "P10376": [
            "agricultural-and-biological-sciences/markov-chain",
            "computer-science/markov-chain",
            "earth-and-planetary-sciences/markov-chain",
            "economics-econometrics-and-finance/markov-chain",
            "materials-science/markov-chain",
            "mathematics/markov-chain",
            "physics-and-astronomy/markov-chain",
            "psychology/markov-chain",
            "social-sciences/markov-chain"
          ],
          "P2892": "C0024828",
          "P950": "XX540042",
          "P6104": {
            "id": "Q8487137",
            "label": "WikiProject Mathematics"
          },
          "P6564": "markov-chains",
          "P3911": "15220-4",
          "P13591": "concept/675ba6ed-5b3f-46ec-8802-b3440b40a160",
          "P1036": "519.233"
        }
      }
    },
    {
      "name": "Discrete-time Markov chain",
      "entity_type": "concept",
      "relation": "uses",
      "relevance": "Explicitly mentioned as a special case that Markov automata encompass.",
      "wikipedia_url": "https://en.wikipedia.org/wiki/Discrete-time_Markov_chain",
      "wikidata": {
        "id": "Q16109430",
        "label": "discrete-time Markov chain",
        "description": "a sequence of random variables in which the value of the next variable depends only on the value of the current variable, and not any variables in the past",
        "aliases": [
          "DTMC"
        ],
        "claims": {
          "subclass_of": "Q176645",
          "opposite_of": {
            "id": "Q176720",
            "label": "continuous-time Markov chain"
          },
          "google_kg_id": "/g/11k6r9vlbt"
        }
      }
    },
    {
      "name": "Continuous-time Markov chain",
      "entity_type": "concept",
      "relation": "uses",
      "relevance": "Explicitly mentioned as a special case that Markov automata encompass.",
      "wikipedia_url": "https://en.wikipedia.org/wiki/Continuous-time_Markov_chain",
      "wikidata": {
        "id": "Q176720",
        "label": "continuous-time Markov chain",
        "description": "stochastic process that satisfies the Markov property (sometimes characterized as \"memorylessness\")",
        "aliases": [
          "CTMC"
        ],
        "claims": {
          "freebase_id": "/m/048f81",
          "subclass_of": "Q176645",
          "opposite_of": {
            "id": "Q16109430",
            "label": "discrete-time Markov chain"
          },
          "openalex_id": "C147080032"
        }
      }
    },
    {
      "name": "Probabilistic automaton",
      "entity_type": "concept",
      "relation": "uses",
      "relevance": "Probabilistic automata are mentioned as related models that can be expressed within the Markov automata framework.",
      "wikipedia_url": "https://en.wikipedia.org/wiki/Probabilistic_automaton",
      "wikidata": {
        "id": "Q176567",
        "label": "probabilistic automaton",
        "description": "generalization of the non-deterministic finite automaton",
        "aliases": [],
        "claims": {
          "britannica_id": "topic/probabilistic-automaton",
          "P2924": "1909457",
          "mag_id": "174784677",
          "freebase_id": "/m/02rgmnj",
          "openalex_id": "C174784677",
          "openalex_topic_id": "229957",
          "described_by_source": "Q124737633",
          "P11514": "veroiatnostnyi-avtomat-33f382",
          "P691": "ph124559"
        }
      }
    },
    {
      "name": "Model checking",
      "entity_type": "method",
      "relation": "uses",
      "relevance": "The paper discusses numerical model checking procedures, which is the core algorithmic technique being applied.",
      "wikipedia_url": "https://en.wikipedia.org/wiki/Model_checking",
      "wikidata": {
        "id": "Q1569697",
        "label": "model checking",
        "description": "verifying whether a finite-state model meets a given specification",
        "aliases": [],
        "claims": {
          "topic_main_category": "Q8637035",
          "freebase_id": "/m/01vjk8",
          "commons_category": "Model checking (computer science)",
          "quora_topic_id": "Model-Checking",
          "mag_id": "110251889",
          "P5106": "modelcheckng",
          "subclass_of": "Q1003030",
          "openalex_id": "C110251889",
          "P12946": "Model+checking",
          "stack_exchange_tag": "https://cs.stackexchange.com/tags/model-checking"
        }
      }
    },
    {
      "name": "Probabilistic CTL",
      "entity_type": "concept",
      "relation": "uses",
      "relevance": "PCTL is explicitly mentioned as one of the temporal logics used for specifying properties of Markov automata.",
      "wikipedia_url": "https://en.wikipedia.org/wiki/Probabilistic_CTL",
      "wikidata": {
        "id": "Q7246845",
        "label": "probabilistic CTL",
        "description": "extension of computation tree logic (CTL) that allows for probabilistic quantification of described properties",
        "aliases": [
          "probabilistic computation tree logic"
        ],
        "claims": {
          "mag_id": "52063229",
          "freebase_id": "/m/0gmnf3",
          "openalex_id": "C52063229",
          "instance_of": "Q781833"
        }
      }
    },
    {
      "name": "Temporal logic",
      "entity_type": "concept",
      "relation": "uses",
      "relevance": "Temporal logics (PCTL and CSL-like) are the formal specification languages for model checking Markov automata.",
      "wikipedia_url": "https://en.wikipedia.org/wiki/Temporal_logic",
      "wikidata": {
        "id": "Q781833",
        "label": "temporal logic",
        "description": "system for representing and reasoning about time",
        "aliases": [],
        "claims": {
          "topic_main_category": {
            "id": "Q8842299",
            "label": "Category:Temporal logic"
          },
          "freebase_id": "/m/01vkqn",
          "P3285": "03B44",
          "subclass_of": {
            "id": "Q1166618",
            "label": "mathematical logic"
          },
          "quora_topic_id": "Temporal-Logic",
          "P3827": "tense-logic",
          "britannica_id": "topic/temporal-logic",
          "P3235": "temporal-logic",
          "commons_category": "Temporal logic",
          "mag_id": "25016198",
          "P8408": "TenseLogic",
          "P4215": "temporal logic",
          "P5106": "temporllogic",
          "P2924": "2333589",
          "openalex_id": "C25016198",
          "P6781": "Definition:Temporal_Logic",
          "P8313": "tidslogik",
          "P12946": "temporal+logic",
          "stack_exchange_tag": "https://cs.stackexchange.com/tags/temporal-logic"
        }
      }
    },
    {
      "name": "Approximation algorithm",
      "entity_type": "method",
      "relation": "proposes",
      "relevance": "The paper proposes a stable approximation scheme for computing time-bounded reachability probabilities.",
      "wikipedia_url": "https://en.wikipedia.org/wiki/Approximation_algorithm",
      "wikidata": {
        "id": "Q621751",
        "label": "approximation algorithm",
        "description": "class of algorithms that find approximate solutions to optimization problems",
        "aliases": [],
        "claims": {
          "subclass_of": {
            "id": "Q8366",
            "label": "algorithm"
          },
          "gnd_id": "4500954-5",
          "freebase_id": "/m/02qc78",
          "P1687": "P1171",
          "topic_main_category": {
            "id": "Q7019556",
            "label": "Category:Approximation algorithms"
          },
          "P5106": "approximatin",
          "different_from": "Q24262840",
          "P1245": "1098668",
          "mag_id": "148764684",
          "loc_id": "sh2009010988",
          "P508": "68574",
          "P268": "16603384f",
          "P8189": "987007475469205171",
          "openalex_id": "C148764684",
          "opposite_of": {
            "id": "Q24963771",
            "label": "exact algorithm"
          },
          "openalex_topic_id": "584576",
          "P10376": [
            "computer-science/approximation-algorithms",
            "social-sciences/approximation-algorithms",
            "computer-science/approximation-algorithm"
          ],
          "P12946": "approximation+algorithm",
          "P13591": "concept/fdc2ae0c-bf65-44a9-925f-fc05addbfadf",
          "P1036": "518.1",
          "stack_exchange_tag": "https://cstheory.stackexchange.com/tags/approximation-algorithms"
        }
      }
    }
  ]
}