{
  "paper_type": "contribution",
  "triples": [
    {
      "name": "Object Constraint Language",
      "entity_type": "tool",
      "relation": "uses",
      "relevance": "OCL is the constraint language that the paper analyzes and translates to first-order logic.",
      "wikipedia_url": "https://en.wikipedia.org/wiki/Object_Constraint_Language",
      "wikidata": {
        "id": "Q1397689",
        "label": null,
        "description": "declarative language",
        "aliases": [],
        "claims": {
          "freebase_id": "/m/024txs",
          "P856": "http://www.omg.org/spec/OCL/",
          "quora_topic_id": "Object-Constraint-Language",
          "mag_id": "133264317",
          "openalex_id": "C133264317",
          "instance_of": "Q1209840",
          "P144": [
            {
              "id": "Q169411",
              "label": "Unified Modeling Language"
            },
            {
              "id": "Q7662832",
              "label": "Syntropy"
            }
          ],
          "openalex_topic_id": "47720"
        }
      }
    },
    {
      "name": "First-order logic",
      "entity_type": "concept",
      "relation": "proposes",
      "relevance": "The paper proposes a mapping from OCL into first-order logic as a novel contribution.",
      "wikipedia_url": "https://en.wikipedia.org/wiki/First-order_logic",
      "wikidata": {
        "id": "Q4055684",
        "label": "first-order logic",
        "description": "collection of formal systems used in mathematics, philosophy, linguistics, and computer science",
        "aliases": [
          "first-order predicate calculus",
          "predicate logic",
          "quantified logic",
          "predicate calculus",
          "quantificational logic",
          "FOL"
        ],
        "claims": {
          "freebase_id": "/m/02yz4",
          "described_by_source": "Q124737636",
          "P3285": "03B10",
          "P3827": "predicate-logic",
          "P3235": "predicate-logic",
          "subclass_of": "Q35148",
          "P2579": {
            "id": "Q1166618",
            "label": "mathematical logic"
          },
          "P3219": "calcul-des-predicats",
          "stack_exchange_tag": [
            "https://math.stackexchange.com/tags/first-order-logic",
            "https://stackoverflow.com/tags/first-order-logic",
            "https://cs.stackexchange.com/tags/first-order-logic",
            "https://proofassistants.stackexchange.com/tags/first-order-logic"
          ],
          "P6564": "predicate-logic",
          "britannica_id": "topic/lower-predicate-calculus",
          "mag_id": "100481476",
          "P7554": "Predicate_calculus",
          "different_from": [
            "Q35148",
            "Q131350632"
          ],
          "P2924": "2179111",
          "P9621": "primo-ordine-teoria-del",
          "P9100": "first-order-logic",
          "openalex_id": [
            "C19689857",
            "C100481476"
          ],
          "P4215": "predicate logic",
          "P10407": [
            "999-2",
            "1000-2"
          ],
          "P6058": "divers/calcul_des_prédicats/82250",
          "P7726": "FirstOrderLogic"
        }
      }
    },
    {
      "name": "Automated theorem proving",
      "entity_type": "tool",
      "relation": "uses",
      "relevance": "The paper uses automated theorem provers as a tool to check unsatisfiability of OCL constraints.",
      "wikipedia_url": "https://en.wikipedia.org/wiki/Automated_theorem_proving",
      "wikidata": {
        "id": "Q431667",
        "label": "automated theorem proving",
        "description": "subfield of automated reasoning dealing with proving theorems by computer programs",
        "aliases": [
          "automated deduction",
          "ATP",
          "theorem proving"
        ],
        "claims": {
          "topic_main_category": {
            "id": "Q8279957",
            "label": "Category:Automated theorem proving"
          },
          "freebase_id": "/m/0_8m",
          "subclass_of": {
            "id": "Q1166618",
            "label": "mathematical logic"
          },
          "quora_topic_id": "Automated-Theorem-Proving",
          "P3827": "automated-theorem-proving",
          "loc_id": "sh85010111",
          "P1245": "1098569",
          "mag_id": "206880738",
          "P8408": "AutomatedTheoremProving",
          "openalex_id": "C206880738",
          "P8189": "987007295721005171",
          "P13591": "concept/8c86a08f-5ce3-4715-9792-1d876bfb05de",
          "P8885": "자동정리증명"
        }
      }
    },
    {
      "name": "Satisfiability modulo theories",
      "entity_type": "concept",
      "relation": "uses",
      "relevance": "The paper uses SMT solvers, which are tools for solving satisfiability modulo theories problems.",
      "wikipedia_url": "https://en.wikipedia.org/wiki/Satisfiability_modulo_theories",
      "wikidata": {
        "id": "Q2067766",
        "label": "satisfiability modulo theories",
        "description": "problem of determining whether a mathematical formula is satisfiable",
        "aliases": [
          "SMT"
        ],
        "claims": {
          "freebase_id": "/m/0d4jbt",
          "instance_of": "Q3262192",
          "mag_id": "164155591",
          "openalex_id": "C164155591",
          "P10374": {
            "id": "Q215206",
            "label": "NP-complete"
          }
        }
      }
    },
    {
      "name": "Constraint satisfaction problem",
      "entity_type": "task",
      "relation": "uses",
      "relevance": "The paper addresses the task of checking constraint satisfaction through unsatisfiability analysis.",
      "wikipedia_url": "https://en.wikipedia.org/wiki/Constraint_satisfaction_problem",
      "wikidata": {
        "id": "Q1128326",
        "label": "constraint satisfaction problem",
        "description": "mathematical problems defined as a set of objects whose state must satisfy a number of constraints or limitations",
        "aliases": [
          "CSP"
        ],
        "claims": {
          "freebase_id": "/m/01f0mv",
          "mag_id": "199622910",
          "topic_main_category": "Q13346239",
          "openalex_id": "C199622910",
          "P10374": {
            "id": "Q215206",
            "label": "NP-complete"
          },
          "instance_of": "Q3435924",
          "P1535": {
            "id": "Q30158686",
            "label": "constraint satisfaction"
          }
        }
      }
    }
  ]
}