[
  {
    "id": "https://openalex.org/W4385900995",
    "doi": "https://doi.org/10.3390/systems11080400",
    "title": "A Comprehensive Review of Recent Research Trends on Unmanned Aerial Vehicles (UAVs)",
    "publication_year": 2023,
    "publication_date": "2023-08-02",
    "cited_by_count": 235,
    "type": "review",
    "language": "en",
    "abstract_inverted_index": {
      "The": [
        0
      ],
      "growing": [
        1
      ],
      "interest": [
        2
      ],
      "in": [
        3,
        25,
        59,
        115,
        147,
        178,
        215
      ],
      "unmanned": [
        4
      ],
      "aerial": [
        5
      ],
      "vehicles": [
        6
      ],
      "(UAVs)": [
        7
      ],
      "from": [
        8,
        119
      ],
      "both": [
        9
      ],
      "the": [
        10,
        32,
        48,
        80,
        95,
        120,
        125,
        165,
        185,
        196,
        216,
        225
      ],
      "scientific": [
        11,
        128
      ],
      "and": [
        12,
        22,
        37,
        67,
        86,
        93,
        135,
        157,
        160,
        174,
        188,
        195,
        212,
        239
      ],
      "industrial": [
        13
      ],
      "sectors": [
        14
      ],
      "has": [
        15
      ],
      "attracted": [
        16
      ],
      "a": [
        17,
        76,
        221
      ],
      "wave": [
        18
      ],
      "of": [
        19,
        35,
        79,
        111,
        127,
        167,
        191,
        207,
        224,
        235,
        243
      ],
      "new": [
        20
      ],
      "researchers": [
        21
      ],
      "substantial": [
        23
      ],
      "investments": [
        24
      ],
      "this": [
        26,
        182,
        228,
        236
      ],
      "expansive": [
        27
      ],
      "field.": [
        28,
        218
      ],
      "However,": [
        29
      ],
      "due": [
        30
      ],
      "to": [
        31,
        62,
        123,
        231
      ],
      "wide": [
        33
      ],
      "range": [
        34
      ],
      "topics": [
        36
      ],
      "subdomains": [
        38
      ],
      "within": [
        39
      ],
      "UAV": [
        40,
        60,
        81,
        179,
        217,
        226
      ],
      "research,": [
        41
      ],
      "newcomers": [
        42
      ],
      "may": [
        43
      ],
      "find": [
        44
      ],
      "themselves": [
        45
      ],
      "overwhelmed": [
        46
      ],
      "by": [
        47,
        98
      ],
      "numerous": [
        49
      ],
      "options": [
        50
      ],
      "available.": [
        51
      ],
      "It": [
        52,
        106,
        202
      ],
      "is": [
        53
      ],
      "therefore": [
        54
      ],
      "crucial": [
        55
      ],
      "for": [
        56,
        144
      ],
      "those": [
        57
      ],
      "involved": [
        58
      ],
      "research": [
        61,
        113,
        133
      ],
      "recognize": [
        63
      ],
      "its": [
        64,
        68
      ],
      "interdisciplinary": [
        65,
        241
      ],
      "nature": [
        66
      ],
      "connections": [
        69
      ],
      "with": [
        70,
        131,
        200
      ],
      "other": [
        71
      ],
      "disciplines.": [
        72
      ],
      "This": [
        73,
        138
      ],
      "paper": [
        74,
        139,
        183,
        229
      ],
      "presents": [
        75
      ],
      "comprehensive": [
        77,
        222
      ],
      "overview": [
        78,
        110,
        206
      ],
      "field,": [
        82,
        227
      ],
      "highlighting": [
        83
      ],
      "recent": [
        84,
        90
      ],
      "trends": [
        85,
        114
      ],
      "advancements.": [
        87
      ],
      "Drawing": [
        88
      ],
      "on": [
        89,
        102
      ],
      "literature": [
        91
      ],
      "reviews": [
        92
      ],
      "surveys,": [
        94
      ],
      "review": [
        96
      ],
      "begins": [
        97
      ],
      "classifying": [
        99
      ],
      "UAVs": [
        100
      ],
      "based": [
        101
      ],
      "their": [
        103,
        136,
        193
      ],
      "flight": [
        104
      ],
      "characteristics.": [
        105
      ],
      "then": [
        107
      ],
      "provides": [
        108,
        204
      ],
      "an": [
        109,
        205
      ],
      "current": [
        112,
        208
      ],
      "UAVs,": [
        116,
        148,
        192
      ],
      "utilizing": [
        117
      ],
      "data": [
        118
      ],
      "Scopus": [
        121
      ],
      "database": [
        122
      ],
      "quantify": [
        124
      ],
      "number": [
        126
      ],
      "documents": [
        129
      ],
      "associated": [
        130,
        199
      ],
      "each": [
        132
      ],
      "direction": [
        134
      ],
      "interconnections.": [
        137
      ],
      "also": [
        140,
        203
      ],
      "explores": [
        141
      ],
      "potential": [
        142
      ],
      "areas": [
        143
      ],
      "further": [
        145
      ],
      "development": [
        146,
        166
      ],
      "including": [
        149
      ],
      "communication,": [
        150
      ],
      "artificial": [
        151
      ],
      "intelligence,": [
        152
      ],
      "remote": [
        153
      ],
      "sensing,": [
        154
      ],
      "miniaturization,": [
        155
      ],
      "swarming": [
        156
      ],
      "cooperative": [
        158
      ],
      "control,": [
        159,
        169
      ],
      "transformability.": [
        161
      ],
      "Additionally,": [
        162
      ],
      "it": [
        163
      ],
      "discusses": [
        164
      ],
      "aircraft": [
        168
      ],
      "commonly": [
        170
      ],
      "used": [
        171
      ],
      "control": [
        172,
        176
      ],
      "techniques,": [
        173
      ],
      "appropriate": [
        175
      ],
      "algorithms": [
        177
      ],
      "research.": [
        180,
        244
      ],
      "Furthermore,": [
        181
      ],
      "addresses": [
        184
      ],
      "general": [
        186
      ],
      "hardware": [
        187,
        213
      ],
      "software": [
        189,
        211
      ],
      "architecture": [
        190
      ],
      "applications,": [
        194
      ],
      "key": [
        197
      ],
      "issues": [
        198
      ],
      "them.": [
        201
      ],
      "open": [
        209
      ],
      "source": [
        210
      ],
      "projects": [
        214
      ],
      "By": [
        219
      ],
      "presenting": [
        220
      ],
      "view": [
        223
      ],
      "aims": [
        230
      ],
      "enhance": [
        232
      ],
      "our": [
        233
      ],
      "understanding": [
        234
      ],
      "rapidly": [
        237
      ],
      "evolving": [
        238
      ],
      "highly": [
        240
      ],
      "area": [
        242
      ]
    },
    "topics": [
      {
        "id": "https://openalex.org/T11133",
        "display_name": "UAV Applications and Optimization",
        "score": 0.9995999932289124,
        "subfield": {
          "id": "https://openalex.org/subfields/2202",
          "display_name": "Aerospace Engineering"
        },
        "field": {
          "id": "https://openalex.org/fields/22",
          "display_name": "Engineering"
        },
        "domain": {
          "id": "https://openalex.org/domains/3",
          "display_name": "Physical Sciences"
        }
      },
      {
        "id": "https://openalex.org/T10249",
        "display_name": "Distributed Control Multi-Agent Systems",
        "score": 0.9958000183105469,
        "subfield": {
          "id": "https://openalex.org/subfields/1705",
          "display_name": "Computer Networks and Communications"
        },
        "field": {
          "id": "https://openalex.org/fields/17",
          "display_name": "Computer Science"
        },
        "domain": {
          "id": "https://openalex.org/domains/3",
          "display_name": "Physical Sciences"
        }
      },
      {
        "id": "https://openalex.org/T10191",
        "display_name": "Robotics and Sensor-Based Localization",
        "score": 0.9789000153541565,
        "subfield": {
          "id": "https://openalex.org/subfields/2202",
          "display_name": "Aerospace Engineering"
        },
        "field": {
          "id": "https://openalex.org/fields/22",
          "display_name": "Engineering"
        },
        "domain": {
          "id": "https://openalex.org/domains/3",
          "display_name": "Physical Sciences"
        }
      }
    ],
    "primary_topic": {
      "id": "https://openalex.org/T11133",
      "display_name": "UAV Applications and Optimization",
      "score": 0.9995999932289124,
      "subfield": {
        "id": "https://openalex.org/subfields/2202",
        "display_name": "Aerospace Engineering"
      },
      "field": {
        "id": "https://openalex.org/fields/22",
        "display_name": "Engineering"
      },
      "domain": {
        "id": "https://openalex.org/domains/3",
        "display_name": "Physical Sciences"
      }
    },
    "keywords": [
      {
        "id": "https://openalex.org/keywords/expansive",
        "display_name": "Expansive",
        "score": 0.6680481433868408
      },
      {
        "id": "https://openalex.org/keywords/systems-engineering",
        "display_name": "Systems engineering",
        "score": 0.5949640870094299
      },
      {
        "id": "https://openalex.org/keywords/field",
        "display_name": "Field (mathematics)",
        "score": 0.584527313709259
      },
      {
        "id": "https://openalex.org/keywords/drone",
        "display_name": "Drone",
        "score": 0.5747306942939758
      },
      {
        "id": "https://openalex.org/keywords/computer-science",
        "display_name": "Computer science",
        "score": 0.5375961661338806
      },
      {
        "id": "https://openalex.org/keywords/open-research",
        "display_name": "Open research",
        "score": 0.49761608242988586
      },
      {
        "id": "https://openalex.org/keywords/data-science",
        "display_name": "Data science",
        "score": 0.4677066504955292
      },
      {
        "id": "https://openalex.org/keywords/software",
        "display_name": "Software",
        "score": 0.4515874683856964
      },
      {
        "id": "https://openalex.org/keywords/architecture",
        "display_name": "Architecture",
        "score": 0.44717124104499817
      },
      {
        "id": "https://openalex.org/keywords/key",
        "display_name": "Key (lock)",
        "score": 0.4132433533668518
      },
      {
        "id": "https://openalex.org/keywords/engineering",
        "display_name": "Engineering",
        "score": 0.264374315738678
      },
      {
        "id": "https://openalex.org/keywords/computer-security",
        "display_name": "Computer security",
        "score": 0.1321220099925995
      },
      {
        "id": "https://openalex.org/keywords/world-wide-web",
        "display_name": "World Wide Web",
        "score": 0.12470367550849915
      }
    ],
    "concepts": [
      {
        "id": "https://openalex.org/C2780502288",
        "wikidata": "https://www.wikidata.org/wiki/Q28838156",
        "display_name": "Expansive",
        "level": 3,
        "score": 0.6680481433868408
      },
      {
        "id": "https://openalex.org/C201995342",
        "wikidata": "https://www.wikidata.org/wiki/Q682496",
        "display_name": "Systems engineering",
        "level": 1,
        "score": 0.5949640870094299
      },
      {
        "id": "https://openalex.org/C9652623",
        "wikidata": "https://www.wikidata.org/wiki/Q190109",
        "display_name": "Field (mathematics)",
        "level": 2,
        "score": 0.584527313709259
      },
      {
        "id": "https://openalex.org/C59519942",
        "wikidata": "https://www.wikidata.org/wiki/Q650665",
        "display_name": "Drone",
        "level": 2,
        "score": 0.5747306942939758
      },
      {
        "id": "https://openalex.org/C41008148",
        "wikidata": "https://www.wikidata.org/wiki/Q21198",
        "display_name": "Computer science",
        "level": 0,
        "score": 0.5375961661338806
      },
      {
        "id": "https://openalex.org/C2778464652",
        "wikidata": "https://www.wikidata.org/wiki/Q309849",
        "display_name": "Open research",
        "level": 2,
        "score": 0.49761608242988586
      },
      {
        "id": "https://openalex.org/C2522767166",
        "wikidata": "https://www.wikidata.org/wiki/Q2374463",
        "display_name": "Data science",
        "level": 1,
        "score": 0.4677066504955292
      },
      {
        "id": "https://openalex.org/C2777904410",
        "wikidata": "https://www.wikidata.org/wiki/Q7397",
        "display_name": "Software",
        "level": 2,
        "score": 0.4515874683856964
      },
      {
        "id": "https://openalex.org/C123657996",
        "wikidata": "https://www.wikidata.org/wiki/Q12271",
        "display_name": "Architecture",
        "level": 2,
        "score": 0.44717124104499817
      },
      {
        "id": "https://openalex.org/C26517878",
        "wikidata": "https://www.wikidata.org/wiki/Q228039",
        "display_name": "Key (lock)",
        "level": 2,
        "score": 0.4132433533668518
      },
      {
        "id": "https://openalex.org/C127413603",
        "wikidata": "https://www.wikidata.org/wiki/Q11023",
        "display_name": "Engineering",
        "level": 0,
        "score": 0.264374315738678
      },
      {
        "id": "https://openalex.org/C38652104",
        "wikidata": "https://www.wikidata.org/wiki/Q3510521",
        "display_name": "Computer security",
        "level": 1,
        "score": 0.1321220099925995
      },
      {
        "id": "https://openalex.org/C136764020",
        "wikidata": "https://www.wikidata.org/wiki/Q466",
        "display_name": "World Wide Web",
        "level": 1,
        "score": 0.12470367550849915
      },
      {
        "id": "https://openalex.org/C202444582",
        "wikidata": "https://www.wikidata.org/wiki/Q837863",
        "display_name": "Pure mathematics",
        "level": 1,
        "score": 0.0
      },
      {
        "id": "https://openalex.org/C86803240",
        "wikidata": "https://www.wikidata.org/wiki/Q420",
        "display_name": "Biology",
        "level": 0,
        "score": 0.0
      },
      {
        "id": "https://openalex.org/C192562407",
        "wikidata": "https://www.wikidata.org/wiki/Q228736",
        "display_name": "Materials science",
        "level": 0,
        "score": 0.0
      },
      {
        "id": "https://openalex.org/C142362112",
        "wikidata": "https://www.wikidata.org/wiki/Q735",
        "display_name": "Art",
        "level": 0,
        "score": 0.0
      },
      {
        "id": "https://openalex.org/C33923547",
        "wikidata": "https://www.wikidata.org/wiki/Q395",
        "display_name": "Mathematics",
        "level": 0,
        "score": 0.0
      },
      {
        "id": "https://openalex.org/C30407753",
        "wikidata": "https://www.wikidata.org/wiki/Q186191",
        "display_name": "Compressive strength",
        "level": 2,
        "score": 0.0
      },
      {
        "id": "https://openalex.org/C153349607",
        "wikidata": "https://www.wikidata.org/wiki/Q36649",
        "display_name": "Visual arts",
        "level": 1,
        "score": 0.0
      },
      {
        "id": "https://openalex.org/C159985019",
        "wikidata": "https://www.wikidata.org/wiki/Q181790",
        "display_name": "Composite material",
        "level": 1,
        "score": 0.0
      },
      {
        "id": "https://openalex.org/C54355233",
        "wikidata": "https://www.wikidata.org/wiki/Q7162",
        "display_name": "Genetics",
        "level": 1,
        "score": 0.0
      },
      {
        "id": "https://openalex.org/C199360897",
        "wikidata": "https://www.wikidata.org/wiki/Q9143",
        "display_name": "Programming language",
        "level": 1,
        "score": 0.0
      }
    ],
    "referenced_works": [
      "https://openalex.org/W4321230314",
      "https://openalex.org/W4321598945",
      "https://openalex.org/W4313575986",
      "https://openalex.org/W4286250636",
      "https://openalex.org/W4223578717",
      "https://openalex.org/W4385337322",
      "https://openalex.org/W4361222892",
      "https://openalex.org/W4313452840",
      "https://openalex.org/W4226332576",
      "https://openalex.org/W4297293381",
      "https://openalex.org/W4224854590",
      "https://openalex.org/W6749102769",
      "https://openalex.org/W4312952070",
      "https://openalex.org/W3084064394",
      "https://openalex.org/W2895889579",
      "https://openalex.org/W4327624012",
      "https://openalex.org/W4220889079",
      "https://openalex.org/W3013204682",
      "https://openalex.org/W4225797003",
      "https://openalex.org/W2010658144",
      "https://openalex.org/W2789880387",
      "https://openalex.org/W3164594912",
      "https://openalex.org/W7005635679",
      "https://openalex.org/W3037780172",
      "https://openalex.org/W2506852226",
      "https://openalex.org/W2902806690",
      "https://openalex.org/W3010653336",
      "https://openalex.org/W4321488634",
      "https://openalex.org/W4313349895",
      "https://openalex.org/W6790139290",
      "https://openalex.org/W3205383004",
      "https://openalex.org/W4324061701",
      "https://openalex.org/W4321497282",
      "https://openalex.org/W2610728744",
      "https://openalex.org/W4200122015",
      "https://openalex.org/W4280496735",
      "https://openalex.org/W3138342693",
      "https://openalex.org/W2986323898",
      "https://openalex.org/W2889458517",
      "https://openalex.org/W2130192595",
      "https://openalex.org/W3023034607",
      "https://openalex.org/W3196860274",
      "https://openalex.org/W2427967923",
      "https://openalex.org/W3033267730",
      "https://openalex.org/W4296915802",
      "https://openalex.org/W2902721117",
      "https://openalex.org/W6848893552",
      "https://openalex.org/W4318499073",
      "https://openalex.org/W2965660127",
      "https://openalex.org/W3134451941",
      "https://openalex.org/W2899898540",
      "https://openalex.org/W2806613708",
      "https://openalex.org/W4224232733",
      "https://openalex.org/W3208471383",
      "https://openalex.org/W4206243099",
      "https://openalex.org/W6838623183",
      "https://openalex.org/W3200667636",
      "https://openalex.org/W2914600382",
      "https://openalex.org/W1969455159",
      "https://openalex.org/W1968716483",
      "https://openalex.org/W2071866183",
      "https://openalex.org/W2084156584",
      "https://openalex.org/W2547617872",
      "https://openalex.org/W3013310826",
      "https://openalex.org/W3215453362",
      "https://openalex.org/W4293767161",
      "https://openalex.org/W4321497764",
      "https://openalex.org/W3090147969",
      "https://openalex.org/W2984634157",
      "https://openalex.org/W1642075362",
      "https://openalex.org/W3014951170",
      "https://openalex.org/W2789779539",
      "https://openalex.org/W2904615053",
      "https://openalex.org/W4287891035",
      "https://openalex.org/W4210594127",
      "https://openalex.org/W4290928366",
      "https://openalex.org/W2954161493",
      "https://openalex.org/W1585334383",
      "https://openalex.org/W2905244835",
      "https://openalex.org/W3193427565",
      "https://openalex.org/W3157579728",
      "https://openalex.org/W6795747911",
      "https://openalex.org/W4293660849",
      "https://openalex.org/W3163961961",
      "https://openalex.org/W2061319289",
      "https://openalex.org/W4307117543",
      "https://openalex.org/W2920915675",
      "https://openalex.org/W2783041906",
      "https://openalex.org/W4225966400",
      "https://openalex.org/W2512695020",
      "https://openalex.org/W4283367635",
      "https://openalex.org/W3194613964",
      "https://openalex.org/W4229064442",
      "https://openalex.org/W2965666581",
      "https://openalex.org/W3034571790",
      "https://openalex.org/W1497579618",
      "https://openalex.org/W4280564686",
      "https://openalex.org/W2973163281",
      "https://openalex.org/W3173137707",
      "https://openalex.org/W2006912800",
      "https://openalex.org/W2539466166",
      "https://openalex.org/W2248841973",
      "https://openalex.org/W4214904220",
      "https://openalex.org/W3209643114",
      "https://openalex.org/W3205184177",
      "https://openalex.org/W6774475168",
      "https://openalex.org/W3094330271",
      "https://openalex.org/W3134092549",
      "https://openalex.org/W2968339166",
      "https://openalex.org/W2765888274",
      "https://openalex.org/W2615478411",
      "https://openalex.org/W2617723903",
      "https://openalex.org/W4288770743",
      "https://openalex.org/W2990239129",
      "https://openalex.org/W3092163236",
      "https://openalex.org/W4213372251",
      "https://openalex.org/W2899516785",
      "https://openalex.org/W2788163438",
      "https://openalex.org/W6842477734",
      "https://openalex.org/W611597954",
      "https://openalex.org/W3213178734",
      "https://openalex.org/W4313316137",
      "https://openalex.org/W2976792973",
      "https://openalex.org/W6799945053",
      "https://openalex.org/W3167935049",
      "https://openalex.org/W7027804239",
      "https://openalex.org/W4206536895",
      "https://openalex.org/W4224940282",
      "https://openalex.org/W6805389014",
      "https://openalex.org/W2624848721",
      "https://openalex.org/W2901139858",
      "https://openalex.org/W2546888793",
      "https://openalex.org/W4312204690",
      "https://openalex.org/W4291653513",
      "https://openalex.org/W4226142707",
      "https://openalex.org/W3133882871",
      "https://openalex.org/W4366425746",
      "https://openalex.org/W4389665836",
      "https://openalex.org/W4366425747",
      "https://openalex.org/W3172675210",
      "https://openalex.org/W4312301659",
      "https://openalex.org/W6854555012",
      "https://openalex.org/W6910144657",
      "https://openalex.org/W4283455220",
      "https://openalex.org/W3015353002",
      "https://openalex.org/W4306292106",
      "https://openalex.org/W2982729292",
      "https://openalex.org/W3168913804",
      "https://openalex.org/W3203424619",
      "https://openalex.org/W3165417815",
      "https://openalex.org/W3204826771",
      "https://openalex.org/W4292979932",
      "https://openalex.org/W2967238999",
      "https://openalex.org/W4283803038",
      "https://openalex.org/W2899428095",
      "https://openalex.org/W4315651159",
      "https://openalex.org/W3085565780",
      "https://openalex.org/W3207108892",
      "https://openalex.org/W6636075138",
      "https://openalex.org/W2607386221",
      "https://openalex.org/W2766120617",
      "https://openalex.org/W7051562904",
      "https://openalex.org/W3154051857",
      "https://openalex.org/W2080456176",
      "https://openalex.org/W3096523944",
      "https://openalex.org/W3035501398",
      "https://openalex.org/W4281487253",
      "https://openalex.org/W2160608755",
      "https://openalex.org/W4323313873",
      "https://openalex.org/W4312127153",
      "https://openalex.org/W4280528974",
      "https://openalex.org/W2905560833",
      "https://openalex.org/W3092021811",
      "https://openalex.org/W4402638613",
      "https://openalex.org/W3046778650",
      "https://openalex.org/W2562652290",
      "https://openalex.org/W6843952168",
      "https://openalex.org/W2783840519",
      "https://openalex.org/W3118722007",
      "https://openalex.org/W2971979296",
      "https://openalex.org/W4312083106",
      "https://openalex.org/W4310153905",
      "https://openalex.org/W4206933963",
      "https://openalex.org/W4225603636",
      "https://openalex.org/W6733519430",
      "https://openalex.org/W3164663456",
      "https://openalex.org/W4307548668",
      "https://openalex.org/W2581915848",
      "https://openalex.org/W2736176402",
      "https://openalex.org/W2888988383",
      "https://openalex.org/W2468242050",
      "https://openalex.org/W3153187775",
      "https://openalex.org/W3184070115",
      "https://openalex.org/W3026191512",
      "https://openalex.org/W2093829425",
      "https://openalex.org/W2059493488",
      "https://openalex.org/W2941449765",
      "https://openalex.org/W2771861361",
      "https://openalex.org/W1983587899",
      "https://openalex.org/W2003688959",
      "https://openalex.org/W2064293659",
      "https://openalex.org/W2109335081",
      "https://openalex.org/W4256152864",
      "https://openalex.org/W2034088441",
      "https://openalex.org/W2134668622",
      "https://openalex.org/W6623243145",
      "https://openalex.org/W2292710506",
      "https://openalex.org/W2991488543",
      "https://openalex.org/W3195306699",
      "https://openalex.org/W3087187818",
      "https://openalex.org/W2156670902",
      "https://openalex.org/W2172700449",
      "https://openalex.org/W2004577376",
      "https://openalex.org/W6766348603",
      "https://openalex.org/W3165280930",
      "https://openalex.org/W2133050889",
      "https://openalex.org/W3113617473",
      "https://openalex.org/W6682405135",
      "https://openalex.org/W4281695827",
      "https://openalex.org/W4307601323",
      "https://openalex.org/W3199415776",
      "https://openalex.org/W4293877019",
      "https://openalex.org/W4205801813",
      "https://openalex.org/W1924992863",
      "https://openalex.org/W3093739429",
      "https://openalex.org/W2989491186",
      "https://openalex.org/W2785914185",
      "https://openalex.org/W2761237338",
      "https://openalex.org/W2964968984",
      "https://openalex.org/W2992240879",
      "https://openalex.org/W3034898916",
      "https://openalex.org/W2970191971",
      "https://openalex.org/W3163699750",
      "https://openalex.org/W2987285449",
      "https://openalex.org/W6762866682",
      "https://openalex.org/W2811016277",
      "https://openalex.org/W4367663869",
      "https://openalex.org/W4281950752",
      "https://openalex.org/W2892322937",
      "https://openalex.org/W2038730444",
      "https://openalex.org/W3208276547",
      "https://openalex.org/W3024824913",
      "https://openalex.org/W3035529248",
      "https://openalex.org/W4221061208",
      "https://openalex.org/W2910646677",
      "https://openalex.org/W2886080584",
      "https://openalex.org/W2970226842",
      "https://openalex.org/W3175174715",
      "https://openalex.org/W4292553941",
      "https://openalex.org/W6717589491",
      "https://openalex.org/W1904614728",
      "https://openalex.org/W2558164413",
      "https://openalex.org/W2169677720",
      "https://openalex.org/W2562509996",
      "https://openalex.org/W4319997608",
      "https://openalex.org/W2593778105",
      "https://openalex.org/W6809572516",
      "https://openalex.org/W3119938903",
      "https://openalex.org/W4220941499",
      "https://openalex.org/W2986358680",
      "https://openalex.org/W4283822762",
      "https://openalex.org/W4282842107",
      "https://openalex.org/W2146384204",
      "https://openalex.org/W2996578934",
      "https://openalex.org/W4283217152",
      "https://openalex.org/W3157932358",
      "https://openalex.org/W4289821439",
      "https://openalex.org/W4283080563",
      "https://openalex.org/W3097484703",
      "https://openalex.org/W4285404531",
      "https://openalex.org/W3043932162",
      "https://openalex.org/W3030859533",
      "https://openalex.org/W3196407145",
      "https://openalex.org/W3128370569",
      "https://openalex.org/W3211871446",
      "https://openalex.org/W2899096839",
      "https://openalex.org/W2131211137",
      "https://openalex.org/W2742060345",
      "https://openalex.org/W6838187099",
      "https://openalex.org/W1986065507",
      "https://openalex.org/W3126526612",
      "https://openalex.org/W2070982420",
      "https://openalex.org/W2166741066",
      "https://openalex.org/W4293207187",
      "https://openalex.org/W2914859151",
      "https://openalex.org/W6750448347",
      "https://openalex.org/W3125113274",
      "https://openalex.org/W6797342289",
      "https://openalex.org/W2967637335",
      "https://openalex.org/W3198804470",
      "https://openalex.org/W3216026299",
      "https://openalex.org/W2992853805",
      "https://openalex.org/W2100716407",
      "https://openalex.org/W2914933448",
      "https://openalex.org/W2884477931",
      "https://openalex.org/W3007884752",
      "https://openalex.org/W2048846187",
      "https://openalex.org/W3034172770",
      "https://openalex.org/W3093867020",
      "https://openalex.org/W4309703408",
      "https://openalex.org/W6802135417",
      "https://openalex.org/W4205381605",
      "https://openalex.org/W4298003785",
      "https://openalex.org/W4282975830",
      "https://openalex.org/W2963513677",
      "https://openalex.org/W3084665263",
      "https://openalex.org/W4317910376",
      "https://openalex.org/W4292388346",
      "https://openalex.org/W2735897556",
      "https://openalex.org/W2281266019",
      "https://openalex.org/W2811061429",
      "https://openalex.org/W4295854421",
      "https://openalex.org/W4281752023",
      "https://openalex.org/W3196724554",
      "https://openalex.org/W2018855542",
      "https://openalex.org/W6774585219",
      "https://openalex.org/W2527386436",
      "https://openalex.org/W4213147678",
      "https://openalex.org/W3213342001",
      "https://openalex.org/W3216224295",
      "https://openalex.org/W4320004386",
      "https://openalex.org/W3215181416",
      "https://openalex.org/W2964919466",
      "https://openalex.org/W4394828156",
      "https://openalex.org/W4256153703",
      "https://openalex.org/W2798224074",
      "https://openalex.org/W832757850",
      "https://openalex.org/W1601199373",
      "https://openalex.org/W3192433332",
      "https://openalex.org/W4316506832",
      "https://openalex.org/W4297983285",
      "https://openalex.org/W3006165903",
      "https://openalex.org/W4200338404",
      "https://openalex.org/W3183898570",
      "https://openalex.org/W2431157298",
      "https://openalex.org/W2792449130",
      "https://openalex.org/W4213412781",
      "https://openalex.org/W2153296213",
      "https://openalex.org/W3215514448",
      "https://openalex.org/W3203449478",
      "https://openalex.org/W3101738542",
      "https://openalex.org/W3165817384",
      "https://openalex.org/W4280581362",
      "https://openalex.org/W2947718215",
      "https://openalex.org/W3171137753",
      "https://openalex.org/W3009924815",
      "https://openalex.org/W2589313818",
      "https://openalex.org/W4280509219"
    ],
    "related_works": [
      "https://openalex.org/W4229448053",
      "https://openalex.org/W2059768187",
      "https://openalex.org/W4247925126",
      "https://openalex.org/W4312858960",
      "https://openalex.org/W4386036939",
      "https://openalex.org/W4327774218",
      "https://openalex.org/W3206445629",
      "https://openalex.org/W2605096541",
      "https://openalex.org/W3200286695",
      "https://openalex.org/W4379143281"
    ],
    "best_oa_location": {
      "id": "doi:10.3390/systems11080400",
      "is_oa": true,
      "landing_page_url": "https://doi.org/10.3390/systems11080400",
      "pdf_url": "https://www.mdpi.com/2079-8954/11/8/400/pdf?version=1691051996",
      "source": {
        "id": "https://openalex.org/S4210219410",
        "display_name": "Systems",
        "issn_l": "2079-8954",
        "issn": [
          "2079-8954"
        ],
        "is_oa": true,
        "is_in_doaj": true,
        "is_core": true,
        "host_organization": "https://openalex.org/P4310310987",
        "host_organization_name": "Multidisciplinary Digital Publishing Institute",
        "host_organization_lineage": [
          "https://openalex.org/P4310310987"
        ],
        "host_organization_lineage_names": [
          "Multidisciplinary Digital Publishing Institute"
        ],
        "type": "journal"
      },
      "license": "cc-by",
      "license_id": "https://openalex.org/licenses/cc-by",
      "version": "publishedVersion",
      "is_accepted": true,
      "is_published": true,
      "raw_source_name": "Systems",
      "raw_type": "journal-article"
    },
    "open_access": {
      "is_oa": true,
      "oa_status": "gold",
      "oa_url": "https://www.mdpi.com/2079-8954/11/8/400/pdf?version=1691051996",
      "any_repository_has_fulltext": false
    },
    "authorships": [
      {
        "author_position": "first",
        "author": {
          "id": "https://openalex.org/A5092654413",
          "display_name": "Khaled Telli",
          "orcid": "https://orcid.org/0000-0001-7896-9733"
        },
        "institutions": [
          {
            "id": "https://openalex.org/I132806614",
            "display_name": "University of Dubai",
            "ror": "https://ror.org/05h0z7c09",
            "country_code": "AE",
            "type": "education",
            "lineage": [
              "https://openalex.org/I132806614"
            ]
          },
          {
            "id": "https://openalex.org/I206961696",
            "display_name": "University of Biskra",
            "ror": "https://ror.org/05fr5y859",
            "country_code": "DZ",
            "type": "education",
            "lineage": [
              "https://openalex.org/I206961696"
            ]
          }
        ],
        "countries": [
          "AE",
          "DZ"
        ],
        "is_corresponding": false,
        "raw_author_name": "Khaled Telli",
        "raw_affiliation_strings": [
          "College of Engineering and Information Technology, University of Dubai, Dubai 14143, United Arab Emirates",
          "Energy Systems Modelling (MSE) Laboratory, Mohamed Khider University, Biskra 07000, Algeria"
        ],
        "affiliations": [
          {
            "raw_affiliation_string": "Energy Systems Modelling (MSE) Laboratory, Mohamed Khider University, Biskra 07000, Algeria",
            "institution_ids": [
              "https://openalex.org/I206961696"
            ]
          },
          {
            "raw_affiliation_string": "College of Engineering and Information Technology, University of Dubai, Dubai 14143, United Arab Emirates",
            "institution_ids": [
              "https://openalex.org/I132806614"
            ]
          }
        ]
      },
      {
        "author_position": "middle",
        "author": {
          "id": "https://openalex.org/A5080320187",
          "display_name": "Okba Kraa",
          "orcid": "https://orcid.org/0000-0002-0211-2220"
        },
        "institutions": [
          {
            "id": "https://openalex.org/I206961696",
            "display_name": "University of Biskra",
            "ror": "https://ror.org/05fr5y859",
            "country_code": "DZ",
            "type": "education",
            "lineage": [
              "https://openalex.org/I206961696"
            ]
          }
        ],
        "countries": [
          "DZ"
        ],
        "is_corresponding": false,
        "raw_author_name": "Okba Kraa",
        "raw_affiliation_strings": [
          "Energy Systems Modelling (MSE) Laboratory, Mohamed Khider University, Biskra 07000, Algeria"
        ],
        "affiliations": [
          {
            "raw_affiliation_string": "Energy Systems Modelling (MSE) Laboratory, Mohamed Khider University, Biskra 07000, Algeria",
            "institution_ids": [
              "https://openalex.org/I206961696"
            ]
          }
        ]
      },
      {
        "author_position": "middle",
        "author": {
          "id": "https://openalex.org/A5037331113",
          "display_name": "Yassine Himeur",
          "orcid": "https://orcid.org/0000-0001-8904-5587"
        },
        "institutions": [
          {
            "id": "https://openalex.org/I132806614",
            "display_name": "University of Dubai",
            "ror": "https://ror.org/05h0z7c09",
            "country_code": "AE",
            "type": "education",
            "lineage": [
              "https://openalex.org/I132806614"
            ]
          }
        ],
        "countries": [
          "AE"
        ],
        "is_corresponding": true,
        "raw_author_name": "Yassine Himeur",
        "raw_affiliation_strings": [
          "College of Engineering and Information Technology, University of Dubai, Dubai 14143, United Arab Emirates"
        ],
        "affiliations": [
          {
            "raw_affiliation_string": "College of Engineering and Information Technology, University of Dubai, Dubai 14143, United Arab Emirates",
            "institution_ids": [
              "https://openalex.org/I132806614"
            ]
          }
        ]
      },
      {
        "author_position": "middle",
        "author": {
          "id": "https://openalex.org/A5055308914",
          "display_name": "Abdelmalik Ouamane",
          "orcid": "https://orcid.org/0000-0003-2549-5188"
        },
        "institutions": [
          {
            "id": "https://openalex.org/I206961696",
            "display_name": "University of Biskra",
            "ror": "https://ror.org/05fr5y859",
            "country_code": "DZ",
            "type": "education",
            "lineage": [
              "https://openalex.org/I206961696"
            ]
          }
        ],
        "countries": [
          "DZ"
        ],
        "is_corresponding": false,
        "raw_author_name": "Abdelmalik Ouamane",
        "raw_affiliation_strings": [
          "Laboratory of LI3C, Mohamed Khider University, Biskra 07000, Algeria"
        ],
        "affiliations": [
          {
            "raw_affiliation_string": "Laboratory of LI3C, Mohamed Khider University, Biskra 07000, Algeria",
            "institution_ids": [
              "https://openalex.org/I206961696"
            ]
          }
        ]
      },
      {
        "author_position": "middle",
        "author": {
          "id": "https://openalex.org/A5034274690",
          "display_name": "Mohamed Boumehraz",
          "orcid": "https://orcid.org/0000-0002-2285-4686"
        },
        "institutions": [
          {
            "id": "https://openalex.org/I206961696",
            "display_name": "University of Biskra",
            "ror": "https://ror.org/05fr5y859",
            "country_code": "DZ",
            "type": "education",
            "lineage": [
              "https://openalex.org/I206961696"
            ]
          }
        ],
        "countries": [
          "DZ"
        ],
        "is_corresponding": false,
        "raw_author_name": "Mohamed Boumehraz",
        "raw_affiliation_strings": [
          "Energy Systems Modelling (MSE) Laboratory, Mohamed Khider University, Biskra 07000, Algeria"
        ],
        "affiliations": [
          {
            "raw_affiliation_string": "Energy Systems Modelling (MSE) Laboratory, Mohamed Khider University, Biskra 07000, Algeria",
            "institution_ids": [
              "https://openalex.org/I206961696"
            ]
          }
        ]
      },
      {
        "author_position": "middle",
        "author": {
          "id": "https://openalex.org/A5003417758",
          "display_name": "Shadi Atalla",
          "orcid": "https://orcid.org/0000-0003-3017-9243"
        },
        "institutions": [
          {
            "id": "https://openalex.org/I132806614",
            "display_name": "University of Dubai",
            "ror": "https://ror.org/05h0z7c09",
            "country_code": "AE",
            "type": "education",
            "lineage": [
              "https://openalex.org/I132806614"
            ]
          }
        ],
        "countries": [
          "AE"
        ],
        "is_corresponding": false,
        "raw_author_name": "Shadi Atalla",
        "raw_affiliation_strings": [
          "College of Engineering and Information Technology, University of Dubai, Dubai 14143, United Arab Emirates"
        ],
        "affiliations": [
          {
            "raw_affiliation_string": "College of Engineering and Information Technology, University of Dubai, Dubai 14143, United Arab Emirates",
            "institution_ids": [
              "https://openalex.org/I132806614"
            ]
          }
        ]
      },
      {
        "author_position": "last",
        "author": {
          "id": "https://openalex.org/A5081414719",
          "display_name": "Wathiq Mansoor",
          "orcid": "https://orcid.org/0000-0003-2784-5188"
        },
        "institutions": [
          {
            "id": "https://openalex.org/I132806614",
            "display_name": "University of Dubai",
            "ror": "https://ror.org/05h0z7c09",
            "country_code": "AE",
            "type": "education",
            "lineage": [
              "https://openalex.org/I132806614"
            ]
          }
        ],
        "countries": [
          "AE"
        ],
        "is_corresponding": false,
        "raw_author_name": "Wathiq Mansoor",
        "raw_affiliation_strings": [
          "College of Engineering and Information Technology, University of Dubai, Dubai 14143, United Arab Emirates"
        ],
        "affiliations": [
          {
            "raw_affiliation_string": "College of Engineering and Information Technology, University of Dubai, Dubai 14143, United Arab Emirates",
            "institution_ids": [
              "https://openalex.org/I132806614"
            ]
          }
        ]
      }
    ],
    "biblio": {
      "volume": "11",
      "issue": "8",
      "first_page": "400",
      "last_page": "400"
    }
  },
  {
    "id": "https://openalex.org/W4387831891",
    "doi": "https://doi.org/10.1109/tase.2023.3324397",
    "title": "An Improved Predefined-Time Adaptive Neural Control Approach for Nonlinear Multiagent Systems",
    "publication_year": 2023,
    "publication_date": "2023-10-20",
    "cited_by_count": 233,
    "type": "article",
    "language": "en",
    "abstract_inverted_index": {
      "This": [
        0,
        117,
        161
      ],
      "paper": [
        1,
        28,
        162
      ],
      "focuses": [
        2
      ],
      "on": [
        3
      ],
      "the": [
        4,
        19,
        23,
        37,
        42,
        47,
        51,
        59,
        77,
        82,
        89,
        96,
        101,
        120,
        127,
        132,
        138,
        142,
        150,
        166,
        198,
        218,
        228,
        231,
        236,
        262,
        267,
        281,
        290,
        296,
        299
      ],
      "predefined-time": [
        5,
        24,
        34,
        109,
        121,
        167,
        191,
        199,
        203,
        220,
        240,
        258
      ],
      "adaptive": [
        6,
        106,
        241
      ],
      "neural": [
        7,
        97,
        242
      ],
      "tracking": [
        8,
        110
      ],
      "control": [
        9,
        25,
        111,
        168,
        224,
        243
      ],
      "problem": [
        10,
        169
      ],
      "for": [
        11,
        32,
        114,
        170,
        245
      ],
      "nonlinear": [
        12,
        115
      ],
      "multiagent": [
        13
      ],
      "systems": [
        14,
        183,
        186
      ],
      "(MASs).": [
        15
      ],
      "In": [
        16
      ],
      "contrast": [
        17
      ],
      "to": [
        18,
        49,
        55,
        108,
        135,
        159,
        164,
        264
      ],
      "existing": [
        20,
        190,
        219
      ],
      "results": [
        21
      ],
      "of": [
        22,
        39,
        123,
        149,
        230,
        280,
        298
      ],
      "methods,": [
        26
      ],
      "this": [
        27
      ],
      "introduces": [
        29
      ],
      "a": [
        30,
        66,
        70,
        215,
        239,
        278
      ],
      "lemma": [
        31,
        79
      ],
      "achieving": [
        33,
        202
      ],
      "stability": [
        35,
        122
      ],
      "within": [
        36,
        126,
        197,
        255
      ],
      "framework": [
        38
      ],
      "backstepping,": [
        40
      ],
      "and": [
        41,
        58,
        100,
        147,
        201,
        277
      ],
      "primary": [
        43
      ],
      "distinguishing": [
        44
      ],
      "feature": [
        45
      ],
      "is": [
        46,
        73,
        112,
        247
      ],
      "ability": [
        48
      ],
      "predefine": [
        50
      ],
      "convergence": [
        52,
        83,
        196,
        204,
        208
      ],
      "time": [
        53,
        103,
        209,
        283
      ],
      "according": [
        54
      ],
      "user": [
        56,
        90
      ],
      "specifications": [
        57
      ],
      "controller": [
        60,
        291
      ],
      "design": [
        61,
        292
      ],
      "process": [
        62,
        229,
        297
      ],
      "being": [
        63
      ],
      "influenced": [
        64
      ],
      "by": [
        65,
        75,
        88,
        94
      ],
      "singular": [
        67
      ],
      "parameter.": [
        68
      ],
      "Meanwhile,": [
        69
      ],
      "numerical": [
        71
      ],
      "example": [
        72
      ],
      "presented": [
        74,
        113
      ],
      "using": [
        76,
        95
      ],
      "proposed": [
        78,
        151
      ],
      "such": [
        80,
        179
      ],
      "that": [
        81,
        252
      ],
      "performance": [
        84
      ],
      "can": [
        85,
        173,
        250
      ],
      "be": [
        86,
        174
      ],
      "ensured": [
        87
      ],
      "practical": [
        91
      ],
      "specification.": [
        92
      ],
      "Moreover,": [
        93,
        217,
        273
      ],
      "networks": [
        98
      ],
      "(NNs)": [
        99
      ],
      "finite": [
        102,
        282
      ],
      "differentiators,": [
        104
      ],
      "an": [
        105,
        206
      ],
      "approach": [
        107
      ],
      "MASs.": [
        116
      ],
      "method": [
        118,
        244
      ],
      "ensures": [
        119
      ],
      "all": [
        124,
        253
      ],
      "signals": [
        125,
        254
      ],
      "MASs,": [
        128,
        171
      ],
      "while": [
        129,
        260
      ],
      "also": [
        130
      ],
      "enabling": [
        131,
        261
      ],
      "followers&amp;#x2019;": [
        133
      ],
      "outputs": [
        134
      ],
      "accurately": [
        136,
        265
      ],
      "track": [
        137,
        266
      ],
      "desired": [
        139,
        268
      ],
      "trajectory": [
        140,
        269
      ],
      "with": [
        141,
        205,
        270
      ],
      "predefined": [
        143,
        271
      ],
      "time.": [
        144,
        272
      ],
      "The": [
        145,
        189
      ],
      "effectiveness": [
        146
      ],
      "merits": [
        148
      ],
      "scheme": [
        152
      ],
      "are": [
        153,
        257,
        287
      ],
      "substantiated": [
        154
      ],
      "through": [
        155
      ],
      "simulation": [
        156
      ],
      "results.": [
        157
      ],
      "&lt;italic&gt;Note": [
        158
      ],
      "Practitioners&lt;/italic&gt;&amp;#x2014;": [
        160
      ],
      "aims": [
        163
      ],
      "address": [
        165,
        235
      ],
      "which": [
        172,
        226,
        249,
        294
      ],
      "widely": [
        175
      ],
      "used": [
        176
      ],
      "in": [
        177,
        289
      ],
      "practice,": [
        178
      ],
      "as": [
        180
      ],
      "vehicular": [
        181
      ],
      "platoon": [
        182
      ],
      "control,": [
        184,
        187
      ],
      "teleoperation": [
        185
      ],
      "etc.": [
        188
      ],
      "methods": [
        192,
        221
      ],
      "only": [
        193,
        274
      ],
      "guarantee": [
        194,
        251
      ],
      "system": [
        195
      ],
      "interval,": [
        200
      ],
      "exact": [
        207
      ],
      "&lt;inline-formula&gt;": [
        210
      ],
      "&lt;tex-math": [
        211
      ],
      "notation=\"LaTeX\"&gt;$t$&lt;/tex-math&gt;": [
        212
      ],
      "&lt;/inline-formula&gt;": [
        213
      ],
      "remains": [
        214
      ],
      "challenge.": [
        216
      ],
      "contain": [
        222
      ],
      "many": [
        223
      ],
      "parameters,": [
        225
      ],
      "complicates": [
        227
      ],
      "parameter": [
        232,
        276,
        300
      ],
      "tuning.": [
        233,
        301
      ],
      "To": [
        234
      ],
      "aforementioned": [
        237
      ],
      "challenges,": [
        238
      ],
      "MASs": [
        246,
        256
      ],
      "developed,": [
        248
      ],
      "stable": [
        259
      ],
      "followers": [
        263
      ],
      "one": [
        275
      ],
      "pair": [
        279
      ],
      "differentiators": [
        284
      ],
      "designed": [
        285
      ],
      "constants": [
        286
      ],
      "involved": [
        288
      ],
      "process,": [
        293
      ],
      "simplifies": [
        295
      ]
    },
    "topics": [
      {
        "id": "https://openalex.org/T10040",
        "display_name": "Adaptive Control of Nonlinear Systems",
        "score": 0.9995999932289124,
        "subfield": {
          "id": "https://openalex.org/subfields/2207",
          "display_name": "Control and Systems Engineering"
        },
        "field": {
          "id": "https://openalex.org/fields/22",
          "display_name": "Engineering"
        },
        "domain": {
          "id": "https://openalex.org/domains/3",
          "display_name": "Physical Sciences"
        }
      },
      {
        "id": "https://openalex.org/T12794",
        "display_name": "Adaptive Dynamic Programming Control",
        "score": 0.9994999766349792,
        "subfield": {
          "id": "https://openalex.org/subfields/1703",
          "display_name": "Computational Theory and Mathematics"
        },
        "field": {
          "id": "https://openalex.org/fields/17",
          "display_name": "Computer Science"
        },
        "domain": {
          "id": "https://openalex.org/domains/3",
          "display_name": "Physical Sciences"
        }
      },
      {
        "id": "https://openalex.org/T10249",
        "display_name": "Distributed Control Multi-Agent Systems",
        "score": 0.9994000196456909,
        "subfield": {
          "id": "https://openalex.org/subfields/1705",
          "display_name": "Computer Networks and Communications"
        },
        "field": {
          "id": "https://openalex.org/fields/17",
          "display_name": "Computer Science"
        },
        "domain": {
          "id": "https://openalex.org/domains/3",
          "display_name": "Physical Sciences"
        }
      }
    ],
    "primary_topic": {
      "id": "https://openalex.org/T10040",
      "display_name": "Adaptive Control of Nonlinear Systems",
      "score": 0.9995999932289124,
      "subfield": {
        "id": "https://openalex.org/subfields/2207",
        "display_name": "Control and Systems Engineering"
      },
      "field": {
        "id": "https://openalex.org/fields/22",
        "display_name": "Engineering"
      },
      "domain": {
        "id": "https://openalex.org/domains/3",
        "display_name": "Physical Sciences"
      }
    },
    "keywords": [
      {
        "id": "https://openalex.org/keywords/nonlinear-system",
        "display_name": "Nonlinear system",
        "score": 0.6221381425857544
      },
      {
        "id": "https://openalex.org/keywords/computer-science",
        "display_name": "Computer science",
        "score": 0.5890992283821106
      },
      {
        "id": "https://openalex.org/keywords/adaptive-control",
        "display_name": "Adaptive control",
        "score": 0.5467327237129211
      },
      {
        "id": "https://openalex.org/keywords/multi-agent-system",
        "display_name": "Multi-agent system",
        "score": 0.5464602112770081
      },
      {
        "id": "https://openalex.org/keywords/control-theory",
        "display_name": "Control theory (sociology)",
        "score": 0.5136732459068298
      },
      {
        "id": "https://openalex.org/keywords/artificial-neural-network",
        "display_name": "Artificial neural network",
        "score": 0.4756319522857666
      },
      {
        "id": "https://openalex.org/keywords/control-engineering",
        "display_name": "Control engineering",
        "score": 0.44523411989212036
      },
      {
        "id": "https://openalex.org/keywords/control",
        "display_name": "Control (management)",
        "score": 0.43977248668670654
      },
      {
        "id": "https://openalex.org/keywords/control-system",
        "display_name": "Control system",
        "score": 0.4264169931411743
      },
      {
        "id": "https://openalex.org/keywords/engineering",
        "display_name": "Engineering",
        "score": 0.26725873351097107
      },
      {
        "id": "https://openalex.org/keywords/artificial-intelligence",
        "display_name": "Artificial intelligence",
        "score": 0.2610333561897278
      }
    ],
    "concepts": [
      {
        "id": "https://openalex.org/C158622935",
        "wikidata": "https://www.wikidata.org/wiki/Q660848",
        "display_name": "Nonlinear system",
        "level": 2,
        "score": 0.6221381425857544
      },
      {
        "id": "https://openalex.org/C41008148",
        "wikidata": "https://www.wikidata.org/wiki/Q21198",
        "display_name": "Computer science",
        "level": 0,
        "score": 0.5890992283821106
      },
      {
        "id": "https://openalex.org/C107464732",
        "wikidata": "https://www.wikidata.org/wiki/Q235781",
        "display_name": "Adaptive control",
        "level": 3,
        "score": 0.5467327237129211
      },
      {
        "id": "https://openalex.org/C41550386",
        "wikidata": "https://www.wikidata.org/wiki/Q529909",
        "display_name": "Multi-agent system",
        "level": 2,
        "score": 0.5464602112770081
      },
      {
        "id": "https://openalex.org/C47446073",
        "wikidata": "https://www.wikidata.org/wiki/Q5165890",
        "display_name": "Control theory (sociology)",
        "level": 3,
        "score": 0.5136732459068298
      },
      {
        "id": "https://openalex.org/C50644808",
        "wikidata": "https://www.wikidata.org/wiki/Q192776",
        "display_name": "Artificial neural network",
        "level": 2,
        "score": 0.4756319522857666
      },
      {
        "id": "https://openalex.org/C133731056",
        "wikidata": "https://www.wikidata.org/wiki/Q4917288",
        "display_name": "Control engineering",
        "level": 1,
        "score": 0.44523411989212036
      },
      {
        "id": "https://openalex.org/C2775924081",
        "wikidata": "https://www.wikidata.org/wiki/Q55608371",
        "display_name": "Control (management)",
        "level": 2,
        "score": 0.43977248668670654
      },
      {
        "id": "https://openalex.org/C17500928",
        "wikidata": "https://www.wikidata.org/wiki/Q959968",
        "display_name": "Control system",
        "level": 2,
        "score": 0.4264169931411743
      },
      {
        "id": "https://openalex.org/C127413603",
        "wikidata": "https://www.wikidata.org/wiki/Q11023",
        "display_name": "Engineering",
        "level": 0,
        "score": 0.26725873351097107
      },
      {
        "id": "https://openalex.org/C154945302",
        "wikidata": "https://www.wikidata.org/wiki/Q11660",
        "display_name": "Artificial intelligence",
        "level": 1,
        "score": 0.2610333561897278
      },
      {
        "id": "https://openalex.org/C119599485",
        "wikidata": "https://www.wikidata.org/wiki/Q43035",
        "display_name": "Electrical engineering",
        "level": 1,
        "score": 0.0
      },
      {
        "id": "https://openalex.org/C121332964",
        "wikidata": "https://www.wikidata.org/wiki/Q413",
        "display_name": "Physics",
        "level": 0,
        "score": 0.0
      },
      {
        "id": "https://openalex.org/C62520636",
        "wikidata": "https://www.wikidata.org/wiki/Q944",
        "display_name": "Quantum mechanics",
        "level": 1,
        "score": 0.0
      }
    ],
    "referenced_works": [
      "https://openalex.org/W4226053079",
      "https://openalex.org/W1981934471",
      "https://openalex.org/W4285204003",
      "https://openalex.org/W2623264272",
      "https://openalex.org/W2159826786",
      "https://openalex.org/W3174955147",
      "https://openalex.org/W4210714139",
      "https://openalex.org/W2107396783",
      "https://openalex.org/W2065029123",
      "https://openalex.org/W2501602109",
      "https://openalex.org/W2795714409",
      "https://openalex.org/W3008033278",
      "https://openalex.org/W3043661245",
      "https://openalex.org/W2970394640",
      "https://openalex.org/W2301538367",
      "https://openalex.org/W2736101375",
      "https://openalex.org/W4304479610",
      "https://openalex.org/W3157969184",
      "https://openalex.org/W2738417046",
      "https://openalex.org/W4294690681",
      "https://openalex.org/W3028151978",
      "https://openalex.org/W2982367070",
      "https://openalex.org/W3033144026",
      "https://openalex.org/W2341651469",
      "https://openalex.org/W1983294924",
      "https://openalex.org/W3186479045",
      "https://openalex.org/W2741229204",
      "https://openalex.org/W4297032290",
      "https://openalex.org/W4315628851",
      "https://openalex.org/W2030959268",
      "https://openalex.org/W3183394897",
      "https://openalex.org/W3209777177",
      "https://openalex.org/W4385338548",
      "https://openalex.org/W4379531887",
      "https://openalex.org/W4315489467",
      "https://openalex.org/W4319996543",
      "https://openalex.org/W3119450748",
      "https://openalex.org/W4385756606",
      "https://openalex.org/W4285287843",
      "https://openalex.org/W2603406422",
      "https://openalex.org/W3125811536"
    ],
    "related_works": [
      "https://openalex.org/W2969358681",
      "https://openalex.org/W2112559358",
      "https://openalex.org/W2107122120",
      "https://openalex.org/W2615607975",
      "https://openalex.org/W194970950",
      "https://openalex.org/W2342009288",
      "https://openalex.org/W1506477645",
      "https://openalex.org/W2192101006",
      "https://openalex.org/W2116800748",
      "https://openalex.org/W2638730922"
    ],
    "best_oa_location": {
      "id": "pmh:oai:kclpure.kcl.ac.uk:publications/eff56ef2-7117-4e5e-8797-58c17e269329",
      "is_oa": true,
      "landing_page_url": "https://kclpure.kcl.ac.uk/portal/en/publications/eff56ef2-7117-4e5e-8797-58c17e269329",
      "pdf_url": null,
      "source": null,
      "license": "other-oa",
      "license_id": "https://openalex.org/licenses/other-oa",
      "version": "submittedVersion",
      "is_accepted": false,
      "is_published": false,
      "raw_source_name": "Pan , Y , Ji , W , Lam , H-K & Cao , L 2023 , ' An Improved Predefined-time Adaptive Neural Control Approach for Nonlinear Multiagent Systems ' , IEEE TRANSACTIONS ON AUTOMATION SCIENCE AND ENGINEERING , pp. 1-10 . https://doi.org/10.1109/TASE.2023.3324397",
      "raw_type": "article"
    },
    "open_access": {
      "is_oa": true,
      "oa_status": "gold",
      "oa_url": "https://kclpure.kcl.ac.uk/portal/en/publications/eff56ef2-7117-4e5e-8797-58c17e269329",
      "any_repository_has_fulltext": false
    },
    "authorships": [
      {
        "author_position": "first",
        "author": {
          "id": "https://openalex.org/A5032133449",
          "display_name": "Yingnan Pan",
          "orcid": "https://orcid.org/0000-0002-7603-4333"
        },
        "institutions": [
          {
            "id": "https://openalex.org/I97009856",
            "display_name": "Bohai University",
            "ror": "https://ror.org/01kdzej58",
            "country_code": "CN",
            "type": "education",
            "lineage": [
              "https://openalex.org/I97009856"
            ]
          }
        ],
        "countries": [
          "CN"
        ],
        "is_corresponding": false,
        "raw_author_name": "Yingnan Pan",
        "raw_affiliation_strings": [
          "College of Control Science and Engineering, Bohai University, Jinzhou, Liaoning, China"
        ],
        "affiliations": [
          {
            "raw_affiliation_string": "College of Control Science and Engineering, Bohai University, Jinzhou, Liaoning, China",
            "institution_ids": [
              "https://openalex.org/I97009856"
            ]
          }
        ]
      },
      {
        "author_position": "middle",
        "author": {
          "id": "https://openalex.org/A5077940780",
          "display_name": "Weiyu Ji",
          "orcid": "https://orcid.org/0000-0002-7689-8318"
        },
        "institutions": [
          {
            "id": "https://openalex.org/I97009856",
            "display_name": "Bohai University",
            "ror": "https://ror.org/01kdzej58",
            "country_code": "CN",
            "type": "education",
            "lineage": [
              "https://openalex.org/I97009856"
            ]
          }
        ],
        "countries": [
          "CN"
        ],
        "is_corresponding": false,
        "raw_author_name": "Weiyu Ji",
        "raw_affiliation_strings": [
          "College of Control Science and Engineering, Bohai University, Jinzhou, Liaoning, China"
        ],
        "affiliations": [
          {
            "raw_affiliation_string": "College of Control Science and Engineering, Bohai University, Jinzhou, Liaoning, China",
            "institution_ids": [
              "https://openalex.org/I97009856"
            ]
          }
        ]
      },
      {
        "author_position": "middle",
        "author": {
          "id": "https://openalex.org/A5059514204",
          "display_name": "HakKeung Lam",
          "orcid": "https://orcid.org/0000-0002-6572-7265"
        },
        "institutions": [
          {
            "id": "https://openalex.org/I4210119896",
            "display_name": "King's College School",
            "ror": "https://ror.org/02bbqcn27",
            "country_code": "GB",
            "type": "education",
            "lineage": [
              "https://openalex.org/I4210119896"
            ]
          }
        ],
        "countries": [
          "GB"
        ],
        "is_corresponding": false,
        "raw_author_name": "Hak-Keung Lam",
        "raw_affiliation_strings": [
          "Department of Engineering, King&#x2019;s College London, London, U.K"
        ],
        "affiliations": [
          {
            "raw_affiliation_string": "Department of Engineering, King&#x2019;s College London, London, U.K",
            "institution_ids": [
              "https://openalex.org/I4210119896"
            ]
          }
        ]
      },
      {
        "author_position": "last",
        "author": {
          "id": "https://openalex.org/A5027245682",
          "display_name": "Liang Cao",
          "orcid": "https://orcid.org/0000-0002-5698-8527"
        },
        "institutions": [
          {
            "id": "https://openalex.org/I97009856",
            "display_name": "Bohai University",
            "ror": "https://ror.org/01kdzej58",
            "country_code": "CN",
            "type": "education",
            "lineage": [
              "https://openalex.org/I97009856"
            ]
          }
        ],
        "countries": [
          "CN"
        ],
        "is_corresponding": false,
        "raw_author_name": "Liang Cao",
        "raw_affiliation_strings": [
          "College of Mathematical Sciences, Bohai University, Jinzhou, Liaoning, China"
        ],
        "affiliations": [
          {
            "raw_affiliation_string": "College of Mathematical Sciences, Bohai University, Jinzhou, Liaoning, China",
            "institution_ids": [
              "https://openalex.org/I97009856"
            ]
          }
        ]
      }
    ],
    "biblio": {
      "volume": "21",
      "issue": "4",
      "first_page": "6311",
      "last_page": "6320"
    }
  }
]